{
  "produtos": [
    {
      "id": 1749497234672,
      "nome": "Bolo de Morango",
      "descricao": "release of Letraset sheets containing Lorem Ipsum passages, and more recently with desktop publishing software like Aldus PageMaker including versions of Lorem Ipsum.",
      "valor": "120",
      "recheio": "Morango",
      "imagem": "../src/img/Produtos/Morango.jpg"
    },
    {
      "id": 1749497577645,
      "nome": "Bolo de Cenoura",
      "descricao": "release of Letraset sheets containing Lorem Ipsum passages, and more recently with desktop publishing software like Aldus PageMaker including versions of Lorem Ipsum.",
      "valor": "120",
      "recheio": "Cenoura",
      "imagem": "../src/img/Produtos/Cenoura.jpg"
    }
  ],
  "pedidos": []
}